frisquet_api/__init__.py
frisquet_api/client.py
frisquet_api/interface.py
frisquet_api/raw_models.py
frisquet_api-0.1.2.dist-info/METADATA
frisquet_api-0.1.2.dist-info/WHEEL
frisquet_api-0.1.2.dist-info/RECORD
