Metadata-Version: 2.4
Name: frisquet-api
Version: 0.1.2
Summary: Python client for the Frisquet API
Project-URL: Homepage, https://github.com/markkvdb/frisquet-api
Project-URL: Documentation, https://github.com/markkvdb/frisquet-api#readme
Project-URL: Repository, https://github.com/markkvdb/frisquet-api.git
Project-URL: Bug Tracker, https://github.com/markkvdb/frisquet-api/issues
Author-email: markkvdb <github@mvanderbroek.com>
License: MIT
Keywords: boiler,frisquet,heating,iot,smart home
Classifier: Development Status :: 4 - Beta
Classifier: Intended Audience :: Developers
Classifier: License :: OSI Approved :: MIT License
Classifier: Programming Language :: Python :: 3
Classifier: Programming Language :: Python :: 3.12
Classifier: Programming Language :: Python :: 3.13
Classifier: Topic :: Home Automation
Classifier: Topic :: Software Development :: Libraries :: Python Modules
Requires-Python: >=3.12
Requires-Dist: httpx>=0.26.0
Requires-Dist: pydantic>=2.5.0
